MANIFEST.in
README.rst
setup.py
StringDist.egg-info/PKG-INFO
StringDist.egg-info/SOURCES.txt
StringDist.egg-info/dependency_links.txt
StringDist.egg-info/top_level.txt
stringdist/__init__.py
stringdist/cstringdist/cstringdist.c
stringdist/cstringdist/levenshtein.c
stringdist/cstringdist/levenshtein.h
stringdist/cstringdist/levenshtein_shared.c
stringdist/cstringdist/levenshtein_shared.h
stringdist/cstringdist/rdlevenshtein.c
stringdist/cstringdist/rdlevenshtein.h
stringdist/pystringdist/__init__.py
stringdist/pystringdist/levenshtein.py
stringdist/pystringdist/levenshtein_shared.py
stringdist/pystringdist/rdlevenshtein.py