Metadata-Version: 1.1
Name: StringDist
Version: 1.0.8
Summary: This package provides the stringdist module, which includes several functions for calculating string distances. Under the hood, a C extension module is preferentially used for optimal performance, with an automatic fallback to a Python implementation.
Home-page: https://github.com/obulkin/string-dist
Author: Oleg Bulkin
Author-email: o.bulkin@gmail.com
License: MIT
Keywords: string metric string distance edit distance levenshtein damerau-levenshtein optimal string alignment distance
Platform: UNKNOWN
Classifier: Development Status :: 5 - Production/Stable
Classifier: Intended Audience :: Developers
Classifier: License :: OSI Approved :: MIT License
Classifier: Programming Language :: C
Classifier: Programming Language :: Python :: 3
Classifier: Programming Language :: Python :: 3.3
Classifier: Programming Language :: Python :: 3.4
Classifier: Programming Language :: Python :: 3.5
Classifier: Programming Language :: Python :: 3.6
Classifier: Programming Language :: Python :: Implementation :: CPython
Classifier: Programming Language :: Python :: Implementation :: PyPy
Classifier: Programming Language :: Python :: Implementation :: Stackless
Classifier: Topic :: Software Development :: Libraries
